dailymotion_api/__init__.py
dailymotion_api/main.py
dailymotion_api/routes/routes.py
dailymotion_api/static/__init__.py
dailymotion_api/templates/__init__.py
dailymotion_api/templates/home.html
dailymotion_api-0.4.0.dist-info/WHEEL
dailymotion_api-0.4.0.dist-info/METADATA
dailymotion_api-0.4.0.dist-info/RECORD
